{
  "kind": "collectionType",
  "collectionName": "news_collections",
  "info": {
    "singularName": "news-collection",
    "pluralName": "news-collections",
    "displayName": "newsCollection"
  },
  "options": {
    "draftAndPublish": true
  },
  "attributes": {
    "title": {
      "type": "string"
    },
    "description": {
      "type": "richtext"
    },
    "Image": {
      "allowedTypes": [
        "images",
        "files",
        "videos",
        "audios"
      ],
      "type": "media",
      "multiple": true
    }
  }
}
